MANIFEST.in
README.mkd
setup.cfg
setup.py
clyngor_with_clingo/__init__.py
clyngor_with_clingo.egg-info/PKG-INFO
clyngor_with_clingo.egg-info/SOURCES.txt
clyngor_with_clingo.egg-info/dependency_links.txt
clyngor_with_clingo.egg-info/entry_points.txt
clyngor_with_clingo.egg-info/not-zip-safe
clyngor_with_clingo.egg-info/requires.txt
clyngor_with_clingo.egg-info/top_level.txt
clyngor_with_clingo/bin/linux/clingo
clyngor_with_clingo/bin/macos/clingo
clyngor_with_clingo/bin/win/clingo.exe