Metadata-Version: 2.1
Name: clyngor-with-clingo
Version: 5.3.post1
Summary: Installation of clingo binary along clyngor
Home-page: https://github.com/aluriak/clyngor-with-clingo
Author: Lucas Bourneuf
Author-email: lucas.bourneuf@laposte.net
License: GPL
Keywords: Answer Set Programming,wrapper,clingo
Platform: UNKNOWN
Classifier: Development Status :: 4 - Beta
Classifier: Intended Audience :: Science/Research
Classifier: Programming Language :: Python :: 3
Classifier: Programming Language :: Python :: 3.5
Classifier: Programming Language :: Python :: 3.6
Classifier: Programming Language :: Python :: 3.7
Classifier: Programming Language :: ASP
